msvc_interface_zxw/__init__.py
msvc_interface_zxw/msvc_order_payments/__init__.py
msvc_interface_zxw/msvc_user_auth/__init__.py
msvc_interface_zxw/msvc_user_auth/apis.py
msvc_interface_zxw/msvc_user_auth/schemes.py
msvc_interface_zxw-0.0.1.dist-info/METADATA
msvc_interface_zxw-0.0.1.dist-info/WHEEL
msvc_interface_zxw-0.0.1.dist-info/top_level.txt
msvc_interface_zxw-0.0.1.dist-info/RECORD
