Metadata-Version: 2.1
Name: msvc_interface_zxw
Version: 0.0.1
Summary: bug fix: 微服务-用户权限验证 接口，调试完成，测试通过
Home-page: https://github.com/sunshineinwater/
Author: 薛伟的小工具
Author-email: 
Classifier: Programming Language :: Python :: 3.12
Classifier: License :: OSI Approved :: MIT License
Classifier: Operating System :: OS Independent
Requires-Dist: fastapi <0.113,>=0.112.2
Requires-Dist: httpx <=0.27.0,>=0.23.3
